nece/__init__.py
nece/admin.py
nece/exceptions.py
nece/managers.py
nece/models.py
nece/tests.py
django_nece-0.11.dist-info/LICENSE
django_nece-0.11.dist-info/METADATA
django_nece-0.11.dist-info/WHEEL
django_nece-0.11.dist-info/top_level.txt
django_nece-0.11.dist-info/RECORD
