Metadata-Version: 2.1
Name: django-nece
Version: 0.11
Summary: A content translation framework using Postgresql's jsonb field in the background
Home-page: https://github.com/polyconseil/django-nece
Author: Can Mustafa Özdemir
Author-email: canmustafaozdemir@gmail.com
Maintainer: Polyconseil
Maintainer-email: opensource+django-nece@polyconseil.fr
License: BSD License
Download-URL: https://pypi.org/project/django-nece/
Keywords: translations,i18n,language,multilingual
Platform: UNKNOWN
Classifier: Framework :: Django
Classifier: Intended Audience :: Developers
Classifier: License :: OSI Approved :: BSD License
Classifier: Operating System :: OS Independent
Classifier: Programming Language :: Python :: 3.6
Classifier: Programming Language :: Python :: 3.7
Classifier: Programming Language :: Python :: 3.8
Classifier: Programming Language :: Python :: 3.9
Classifier: Topic :: Database
Classifier: Topic :: Internet :: WWW/HTTP :: Dynamic Content
Classifier: Topic :: Text Processing :: Linguistic
Requires-Dist: Django (>=2.2)
Provides-Extra: admin
Requires-Dist: django-admin-json-editor ; extra == 'admin'
Provides-Extra: psycopg2
Requires-Dist: psycopg2 (>=2.8.1) ; extra == 'psycopg2'
Provides-Extra: psycopg2_binary
Requires-Dist: psycopg2-binary (>=2.8.1) ; extra == 'psycopg2_binary'
